[
  {
    "id": 91699,
    "dataBasedName": "Civilians",
    "eventReportIds": [
      40418,
      40435,
      40440,
      40429,
      40419,
      40422,
      40437,
      40438,
      40439,
      40441,
      40446,
      40430,
      40445,
      40417,
      40448,
      40451,
      40453,
      40454,
      40404,
      40414,
      40398,
      40396,
      40385,
      40456
    ],
    "eventTypeSummary": {
      "3": 1.0
    },
    "eventTypes": [
      3
    ],
    "collaborations": {},
    "oppositions": {
      "Government of Bahrain": 24
    },
    "links": [
      {
        "source": "Government of Bahrain",
        "target": "Civilians",
        "linkType": 1,
        "count": 24,
        "reports": [
          40418,
          40435,
          40440,
          40429,
          40419,
          40422,
          40437,
          40438,
          40439,
          40441,
          40446,
          40430,
          40445,
          40417,
          40448,
          40451,
          40453,
          40454,
          40404,
          40414,
          40398,
          40396,
          40385,
          40456
        ]
      }
    ],
    "actorType": 5
  },
  {
    "id": 126,
    "dataBasedName": "Government of Bahrain",
    "eventReportIds": [
      40418,
      40435,
      40440,
      40429,
      40419,
      40422,
      40437,
      40438,
      40439,
      40441,
      40446,
      40430,
      40445,
      40417,
      40448,
      40451,
      40453,
      40454,
      40404,
      40414,
      40398,
      40396,
      40385,
      40456
    ],
    "eventTypeSummary": {
      "3": 1.0
    },
    "eventTypes": [
      3
    ],
    "collaborations": {},
    "oppositions": {
      "Civilians": 24
    },
    "links": [
      {
        "source": "Government of Bahrain",
        "target": "Civilians",
        "linkType": 1,
        "count": 24,
        "reports": [
          40418,
          40435,
          40440,
          40429,
          40419,
          40422,
          40437,
          40438,
          40439,
          40441,
          40446,
          40430,
          40445,
          40417,
          40448,
          40451,
          40453,
          40454,
          40404,
          40414,
          40398,
          40396,
          40385,
          40456
        ]
      }
    ],
    "actorType": 4
  }
]